{"format_version":"1.21.6","credit":"by w11shes","texture_size":[32,32],"textures":{"0":"cosmetics/pitchfork","particle":"cosmetics/pitchfork"},"elements":[{"from":[7,-16,7],"to":[9,16,9],"rotation":{"angle":0,"axis":"y","origin":[7,-16,7]},"faces":{"north":{"uv":[0,0,1,16],"texture":"#0"},"east":{"uv":[2,0,3,16],"texture":"#0"},"south":{"uv":[0,0,1,16],"texture":"#0"},"west":{"uv":[2,0,3,16],"texture":"#0"},"up":{"uv":[2,2,1,1],"texture":"#0"},"down":{"uv":[2,0,1,1],"texture":"#0"}}},{"from":[3.5,5,8],"to":[12.5,23,8.04],"rotation":{"angle":0,"axis":"y","origin":[7.5,16,7]},"faces":{"north":{"uv":[11.5,0,16,9],"texture":"#0"},"south":{"uv":[16,0,11.5,9],"texture":"#0"}}},{"from":[6.75,-4.25,6.75],"to":[9.25,4.25,9.25],"rotation":{"angle":0,"axis":"y","origin":[7,-18,7]},"faces":{"north":{"uv":[1,2,2,6],"texture":"#0","tintindex":0},"east":{"uv":[2,2,1,6],"texture":"#0","tintindex":0},"south":{"uv":[1,2,2,6],"texture":"#0","tintindex":0},"west":{"uv":[2,2,1,6],"texture":"#0","tintindex":0}}},{"from":[7.97,5,5.5],"to":[8,12,10.5],"rotation":{"angle":0,"axis":"y","origin":[8,5,6.5]},"faces":{"east":{"uv":[5.5,0,3,3.5],"texture":"#0"},"west":{"uv":[3,0,5.5,3.5],"texture":"#0"}}},{"from":[7.2,-8.3,6.65],"to":[9.2,-1.3,6.68],"rotation":{"angle":22.5,"axis":"z","origin":[9.2,-1.3,6.65]},"faces":{"north":{"uv":[1,6,2,9.5],"texture":"#0","tintindex":0},"south":{"uv":[2,6,1,9.5],"texture":"#0","tintindex":0}}}],"display":{"thirdperson_righthand":{"rotation":[49,55,-14],"translation":[1.25,6,5.5]},"thirdperson_lefthand":{"rotation":[32,-40,-8],"translation":[1.25,6,5.75]},"firstperson_righthand":{"rotation":[143,159,-177],"translation":[0,5.5,2.5],"scale":[0.7,0.7,0.7]},"firstperson_lefthand":{"rotation":[143,159,-177],"translation":[0,5.5,2.5],"scale":[0.7,0.7,0.7]},"ground":{"translation":[0,12,0],"scale":[0.5,0.5,0.5]},"gui":{"rotation":[-41,-20,-48],"translation":[1.5,1.25,0],"scale":[0.5,0.5,0.5]},"head":{"rotation":[0,-16,-42],"translation":[8.75,-6.75,9.25],"scale":[1.6,1.6,1.6]},"fixed":{"translation":[0,5.5,-1.5]}},"groups":[{"name":"group","origin":[7,-2,7],"color":0,"children":[0,1,2,3,4]}],"mcmodels":"0c4ccce91fb4ad22ca9f47fba5e9e86e"}